ak_sap/__init__.py
ak_sap/wrapper.py
ak_sap/Analyze/__init__.py
ak_sap/Analyze/main.py
ak_sap/Database/__init__.py
ak_sap/Database/table_constants.py
ak_sap/Database/table_structured_data.py
ak_sap/Database/tables.py
ak_sap/Loads/LoadCases.py
ak_sap/Loads/LoadCombos.py
ak_sap/Loads/LoadPatterns.py
ak_sap/Loads/__init__.py
ak_sap/Loads/constants.py
ak_sap/Loads/main.py
ak_sap/Loads/Modal/__init__.py
ak_sap/Loads/Modal/main.py
ak_sap/Loads/Modal/Eigen/main.py
ak_sap/Loads/Modal/Ritz/main.py
ak_sap/Material/constants.py
ak_sap/Material/material.py
ak_sap/Material/types.py
ak_sap/Material/Materials/rebar.py
ak_sap/Model/__init__.py
ak_sap/Model/constants.py
ak_sap/Model/model.py
ak_sap/Object/__init__.py
ak_sap/Object/frame.py
ak_sap/Object/helper.py
ak_sap/Object/obj.py
ak_sap/Object/point.py
ak_sap/Results/Setup.py
ak_sap/Results/__init__.py
ak_sap/Results/main.py
ak_sap/Select/__init__.py
ak_sap/Select/main.py
ak_sap/cli/cli_app.py
ak_sap/cli/update_doc.py
ak_sap/gui/gui_app.py
ak_sap/gui/streamlit/__init__.py
ak_sap/gui/streamlit/config.py
ak_sap/misc/__init__.py
ak_sap/misc/coordinates.py
ak_sap/utils/__init__.py
ak_sap/utils/credentials.py
ak_sap/utils/decorators.py
ak_sap/utils/logger.py
ak_sap-0.0.3.dist-info/entry_points.txt
ak_sap-0.0.3.dist-info/LICENSE
ak_sap-0.0.3.dist-info/WHEEL
ak_sap-0.0.3.dist-info/METADATA
ak_sap-0.0.3.dist-info/RECORD
