Metadata-Version: 2.1
Name: ak_sap
Version: 0.0.3
Summary: Python wrapper for SAP2000 API
Author-email: Arun Kishore <pypi@rpakishore.co.in>
Requires-Python: >=3.11.0
Classifier: License :: OSI Approved :: Mozilla Public License 2.0 (MPL 2.0)
Requires-Dist: comtypes==1.2.0
Requires-Dist: forallpeople==2.6.7
Requires-Dist: pandas==2.1.3
Requires-Dist: rich==13.7.0 ; extra == "cli"
Requires-Dist: typer[all]==0.9.0 ; extra == "cli"
Requires-Dist: ipykernel ; extra == "dev"
Requires-Dist: ipywidgets ; extra == "dev"
Requires-Dist: pandasgui ; extra == "dev"
Requires-Dist: line-profiler ; extra == "dev"
Requires-Dist: streamlit==1.31.0 ; extra == "gui"
Requires-Dist: hilti_profis==0.0.3 ; extra == "gui"
Requires-Dist: pytest==7.4.3 ; extra == "test"
Project-URL: Home, https://github.com/rpakishore/ak_sap
Provides-Extra: cli
Provides-Extra: dev
Provides-Extra: gui
Provides-Extra: test
